ic/__init__.py
ic/agent.py
ic/candid.py
ic/canister.py
ic/certificate.py
ic/client.py
ic/constants.py
ic/identity.py
ic/principal.py
ic/system_state.py
ic/utils.py
ic/common/__init__.py
ic/common/cycles_wallet.py
ic/common/governance.py
ic/common/ledger.py
ic/common/management.py
ic/parser/DIDEmitter.py
ic/parser/DIDLexer.py
ic/parser/DIDParser.py
ic/parser/DIDParserListener.py
ic/parser/__init__.py
ic_py-1.0.1.dist-info/LICENSE
ic_py-1.0.1.dist-info/METADATA
ic_py-1.0.1.dist-info/WHEEL
ic_py-1.0.1.dist-info/top_level.txt
ic_py-1.0.1.dist-info/RECORD
