Metadata-Version: 2.1
Name: ic-py
Version: 1.0.1
Summary: Python Agent Library for the Internet Computer
Home-page: https://github.com/rocklabs-io/ic-py
Author: Rocklabs
Author-email: hello@rocklabs.io
License: UNKNOWN
Keywords: dfinity ic agent
Platform: UNKNOWN
License-File: LICENSE
